learnable_fourier_positional_encoding/__init__.py
learnable_fourier_positional_encoding/learnable_fourier_pos_encoding.py
learnable_fourier_positional_encoding-0.0.1.dist-info/METADATA
learnable_fourier_positional_encoding-0.0.1.dist-info/WHEEL
learnable_fourier_positional_encoding-0.0.1.dist-info/licenses/LICENSE
learnable_fourier_positional_encoding-0.0.1.dist-info/RECORD
