Metadata-Version: 2.3
Name: learnable_fourier_positional_encoding
Version: 0.0.1
Summary: Learnable Fourier Features for Multi-Dimensional Spatial Positional Encoding 
Project-URL: Homepage, https://github.com/willGuimont/learnable_fourier_positional_encoding
Project-URL: Issues, https://github.com/willGuimont/learnable_fourier_positional_encoding/issues
Author-email: William Guimont-Martin <william.guimont-martin@norlab.ulaval.ca>
License: MIT License
License-File: LICENSE
Classifier: License :: OSI Approved :: MIT License
Classifier: Operating System :: OS Independent
Classifier: Programming Language :: Python :: 3
Requires-Python: >=3.8
Requires-Dist: numpy
Requires-Dist: torch
